secret_kv/__init__.py
secret_kv/__main__.py
secret_kv/config/__init__.py
secret_kv/config/base.py
secret_kv/config/context.py
secret_kv/config/keyring_passphrase.py
secret_kv/config/passphrase.py
secret_kv/config/sql_store.py
secret_kv/config/store.py
secret_kv/constants.py
secret_kv/exceptions.py
secret_kv/internal_types.py
secret_kv/py.typed
secret_kv/sentinel.py
secret_kv/simple.py
secret_kv/sql_store.py
secret_kv/store.py
secret_kv/util.py
secret_kv/value.py
secret_kv/version.py
secret_kv-1.3.0.dist-info/entry_points.txt
secret_kv-1.3.0.dist-info/LICENSE
secret_kv-1.3.0.dist-info/WHEEL
secret_kv-1.3.0.dist-info/METADATA
secret_kv-1.3.0.dist-info/RECORD
