Metadata-Version: 2.1
Name: secret-kv
Version: 1.3.0
Summary: Project-local secret key/value storage protected by a single passphrase stored in keyring
Home-page: https://github.com/sammck/secret-kv
License: MIT
Keywords: password,passphrase,secret,keychain,keyring
Author: Sam McKelvie
Author-email: dev@mckelvie.org
Requires-Python: >=3.8,<4.0
Classifier: License :: OSI Approved :: MIT License
Classifier: Programming Language :: Python :: 3
Classifier: Programming Language :: Python :: 3.10
Classifier: Programming Language :: Python :: 3.8
Classifier: Programming Language :: Python :: 3.9
Requires-Dist: argcomplete (>=2.0.0,<3.0.0)
Requires-Dist: colorama (>=0.4.4,<0.5.0)
Requires-Dist: jq (>=1.2.2,<2.0.0)
Requires-Dist: keyring (>=23.5.0,<24.0.0)
Requires-Dist: sqlcipher3 (>=0.4.5,<0.5.0)
Project-URL: Repository, https://github.com/sammck/secret-kv.git
